LICENSE
MANIFEST.in
README.md
requirements.txt
setup.py
scrapyd_dash/__init__.py
scrapyd_dash/admin.py
scrapyd_dash/apps.py
scrapyd_dash/models.py
scrapyd_dash/serializers.py
scrapyd_dash/tests.py
scrapyd_dash/urls.py
scrapyd_dash/views.py
scrapyd_dash.egg-info/PKG-INFO
scrapyd_dash.egg-info/SOURCES.txt
scrapyd_dash.egg-info/dependency_links.txt
scrapyd_dash.egg-info/requires.txt
scrapyd_dash.egg-info/top_level.txt
scrapyd_dash/migrations/0001_initial.py
scrapyd_dash/migrations/__init__.py
scrapyd_dash/operations/check_servers.py
scrapyd_dash/operations/get_log.py
scrapyd_dash/operations/projects_delete.py
scrapyd_dash/operations/projects_list.py
scrapyd_dash/operations/scheduled_tasks.py
scrapyd_dash/operations/spiders_list.py
scrapyd_dash/operations/tasks_add.py
scrapyd_dash/operations/tasks_cancel.py
scrapyd_dash/operations/tasks_list.py
scrapyd_dash/operations/versions_add.py
scrapyd_dash/operations/versions_delete.py
scrapyd_dash/operations/versions_list.py
scrapyd_dash/operations/__pycache__/check_servers.cpython-36.pyc
scrapyd_dash/operations/__pycache__/get_log.cpython-36.pyc
scrapyd_dash/operations/__pycache__/jobs_list.cpython-36.pyc
scrapyd_dash/operations/__pycache__/projects_list.cpython-36.pyc
scrapyd_dash/operations/__pycache__/scheduled_tasks.cpython-36.pyc
scrapyd_dash/operations/__pycache__/spiders_list.cpython-36.pyc
scrapyd_dash/operations/__pycache__/tasks_add.cpython-36.pyc
scrapyd_dash/operations/__pycache__/tasks_cancel.cpython-36.pyc
scrapyd_dash/operations/__pycache__/tasks_list.cpython-36.pyc
scrapyd_dash/operations/__pycache__/versions_list.cpython-36.pyc
scrapyd_dash/static/css/style.css
scrapyd_dash/static/css/style.css.map
scrapyd_dash/static/js/bootstrap-notify.min.js
scrapyd_dash/static/js/chained_dropdown.js
scrapyd_dash/static/js/main.js
scrapyd_dash/static/js/script.js
scrapyd_dash/static/vendors/bootstrap/.babelrc.js
scrapyd_dash/static/vendors/bootstrap/.bower.json
scrapyd_dash/static/vendors/bootstrap/.browserslistrc
scrapyd_dash/static/vendors/bootstrap/.editorconfig
scrapyd_dash/static/vendors/bootstrap/.eslintignore
scrapyd_dash/static/vendors/bootstrap/.eslintrc.json
