Metadata-Version: 2.1
Name: scrapyd-dash
Version: 0.1.2
Summary: A dashboard for scrapy project using scrapyd and logparser
Home-page: https://github.com/Dainius-P/scrapyd-dash
Author: Dainius Preimantas
Author-email: preimantasd@gmail.com
License: BSD License
Platform: UNKNOWN
Classifier: Environment :: Web Environment
Classifier: Framework :: Django
Classifier: Framework :: Django :: 2.2
Classifier: Intended Audience :: Developers
Classifier: License :: OSI Approved :: BSD License
Classifier: Operating System :: OS Independent
Classifier: Programming Language :: Python
Classifier: Programming Language :: Python :: 3.5
Classifier: Programming Language :: Python :: 3.6
Classifier: Topic :: Internet :: WWW/HTTP
Classifier: Topic :: Internet :: WWW/HTTP :: Dynamic Content
